<ModOps>
  <ModOp Type="add" Path="/TextExport/Texts">
    <Text>
      <GUID>1999005388</GUID>
      <Text>Quai de manutention</Text>
    </Text>
    <Text>
      <GUID>1999005645</GUID>
      <Text>Une manipulation appropriée des jetées et les progrès de l’emballage augmentent l’efficacité des quais d’importation.</Text>
    </Text>
    <Text>
      <GUID>1999005646</GUID>
      <Text>Manutention des quais</Text>
    </Text>
    <Text>
      <GUID>1999005647</GUID>
      <Text>Les quais de manutention appropriée et les progrès en matière d’emballage augmentent l’efficacité des quais d’importation, ce qui prolonge la durée de vie de vos marchandises importées.</Text>
    </Text>
  </ModOp>
</ModOps>
